MANIFEST.in
README.txt
requirements.txt
setup.py
distutils.ext/obidistutils/__init__.py
distutils.ext/obidistutils/core.py
distutils.ext/obidistutils/dist.py
distutils.ext/obidistutils/command/__init__.py
distutils.ext/obidistutils/command/build.py
distutils.ext/obidistutils/command/build_cexe.py
distutils.ext/obidistutils/command/build_ctools.py
distutils.ext/obidistutils/command/build_exe.py
distutils.ext/obidistutils/command/build_ext.py
distutils.ext/obidistutils/command/build_files.py
distutils.ext/obidistutils/command/build_filters.py
distutils.ext/obidistutils/command/build_scripts.py
distutils.ext/obidistutils/command/build_sphinx.py
distutils.ext/obidistutils/command/install.py
distutils.ext/obidistutils/command/install_scripts.py
distutils.ext/obidistutils/command/install_sphinx.py
distutils.ext/obidistutils/command/littlebigman.py
distutils.ext/obidistutils/command/pidname.py
distutils.ext/obidistutils/command/sdist.py
distutils.ext/obidistutils/serenity/__init__.py
distutils.ext/obidistutils/serenity/checkpackage.py
distutils.ext/obidistutils/serenity/checkpip.py
distutils.ext/obidistutils/serenity/checkpython.py
distutils.ext/obidistutils/serenity/checksystem.py
distutils.ext/obidistutils/serenity/getcython.py
distutils.ext/obidistutils/serenity/globals.py
distutils.ext/obidistutils/serenity/rerun.py
distutils.ext/obidistutils/serenity/snake.py
distutils.ext/obidistutils/serenity/util.py
distutils.ext/obidistutils/serenity/virtual.py
distutils.ext/obidistutils/serenity/pip/__init__.py
distutils.ext/obidistutils/serenity/pip/__main__.py
distutils.ext/obidistutils/serenity/pip/basecommand.py
distutils.ext/obidistutils/serenity/pip/baseparser.py
distutils.ext/obidistutils/serenity/pip/cmdoptions.py
distutils.ext/obidistutils/serenity/pip/download.py
distutils.ext/obidistutils/serenity/pip/exceptions.py
distutils.ext/obidistutils/serenity/pip/index.py
distutils.ext/obidistutils/serenity/pip/locations.py
distutils.ext/obidistutils/serenity/pip/log.py
src/OBITools.egg-info/PKG-INFO
src/OBITools.egg-info/SOURCES.txt
src/OBITools.egg-info/dependency_links.txt
src/OBITools.egg-info/not-zip-safe
src/OBITools.egg-info/requires.txt
src/OBITools.egg-info/top_level.txt
