Metadata-Version: 1.1
Name: OBITools
Version: 1.2.13
Summary: Scripts and library for sequence analysis
Home-page: http://metabarcoding.org/obitools
Author: Eric Coissac
Author-email: eric@coissac.eu
License: CeCILL-V2
Platform: UNKNOWN
Classifier: Development Status :: 5 - Production/Stable
Classifier: Environment :: Console
Classifier: Intended Audience :: Science/Research
Classifier: License :: Other/Proprietary License
Classifier: Operating System :: Unix
Classifier: Programming Language :: Python
Classifier: Programming Language :: Python :: 2
Classifier: Topic :: Scientific/Engineering :: Bio-Informatics
Classifier: Topic :: Utilities
